README.md
setup.py
tiny_tokenizer/__init__.py
tiny_tokenizer/sentence_tokenizer.py
tiny_tokenizer/tiny_tokenizer_token.py
tiny_tokenizer/word_tokenizer.py
tiny_tokenizer.egg-info/PKG-INFO
tiny_tokenizer.egg-info/SOURCES.txt
tiny_tokenizer.egg-info/dependency_links.txt
tiny_tokenizer.egg-info/requires.txt
tiny_tokenizer.egg-info/top_level.txt
tiny_tokenizer/word_tokenizers/__init__.py
tiny_tokenizer/word_tokenizers/character_tokenizer.py
tiny_tokenizer/word_tokenizers/janome_tokenizer.py
tiny_tokenizer/word_tokenizers/kytea_tokenizer.py
tiny_tokenizer/word_tokenizers/mecab_tokenizer.py
tiny_tokenizer/word_tokenizers/sentencepiece_tokenizer.py
tiny_tokenizer/word_tokenizers/sudachi_tokenizer.py
tiny_tokenizer/word_tokenizers/tokenizer.py
tiny_tokenizer/word_tokenizers/whitespace_tokenizer.py