Metadata-Version: 2.1
Name: tiny-tokenizer
Version: 3.1.0
Summary: Tiny Word/Sentence Tokenizer
Home-page: https://github.com/himkt/tiny_tokenizer
Author: himkt
Author-email: himkt@klis.tsukuba.ac.jp
License: UNKNOWN
Platform: UNKNOWN
Provides-Extra: kytea
Provides-Extra: sudachi
Provides-Extra: sentencepiece
Provides-Extra: all
Provides-Extra: mecab
Provides-Extra: janome
